decipy/__init__.py
decipy/executors.py
decipy/normalizers.py
decipy/weigtings.py
decipy/__pycache__/__init__.cpython-37.pyc
decipy/__pycache__/__init__.cpython-38.pyc
decipy/__pycache__/executors.cpython-37.pyc
decipy/__pycache__/executors.cpython-38.pyc
decipy/__pycache__/normalizers.cpython-37.pyc
decipy/__pycache__/normalizers.cpython-38.pyc
decipy/__pycache__/weigtings.cpython-37.pyc
decipy/__pycache__/weigtings.cpython-38.pyc
decipy/dataset/Salesman_Data.csv
decipy/dataset/Salesman_Data_Test.csv
decipy/dataset/SampleData_10x10.csv
decipy/dataset/SampleData_15x15.csv
decipy/dataset/SampleData_20x20.csv
decipy/dataset/SampleData_5x5.csv
decipy/dataset/decipy_test.xlsx
decipy/utils/__init__.py
decipy/utils/path.py
decipy/utils/version.py
decipy/utils/__pycache__/__init__.cpython-37.pyc
decipy/utils/__pycache__/__init__.cpython-38.pyc
decipy/utils/__pycache__/version.cpython-37.pyc
decipy/utils/__pycache__/version.cpython-38.pyc
decision_python-0.0.1.dist-info/LICENSE
decision_python-0.0.1.dist-info/METADATA
decision_python-0.0.1.dist-info/WHEEL
decision_python-0.0.1.dist-info/top_level.txt
decision_python-0.0.1.dist-info/RECORD
