Metadata-Version: 2.1
Name: decision-python
Version: 0.0.1
Summary: Multi criteria decision making with python
Home-page: https://github.com/justsasri/decipy
Maintainer: Rizki Sasri Dwitama
Maintainer-email: sasri.djproject@gmail.com
License: MIT
Platform: UNKNOWN
Classifier: Development Status :: 3 - Alpha
Classifier: Intended Audience :: Developers
Classifier: License :: OSI Approved :: BSD License
Classifier: Operating System :: OS Independent
Classifier: Programming Language :: Python
Classifier: Topic :: Software Development :: Libraries :: Python Modules
Requires-Dist: pandas (>=1.0)
Requires-Dist: matplotlib (>=3.2)
Requires-Dist: scipy (>=1.4)
